LICENSE
MANIFEST.in
README.md
setup.cfg
setup.py
examples/SPD_rt_smoothing_ex_data.csv
examples/madic_skyline_daily_data.csv
examples/madic_skyline_daily_reference.csv
examples/madic_summary.csv
examples/tutorial.ipynb
examples/.ipynb_checkpoints/tutorial-checkpoint.ipynb
examples/skyline_source_files/skyline_daily_data.sky
examples/skyline_source_files/skyline_daily_data.sky.view
examples/skyline_source_files/skyline_daily_data.skyd
examples/skyline_source_files/skyline_daily_synthetic_reference.sky
examples/skyline_source_files/skyline_daily_synthetic_reference.sky.view
examples/skyline_source_files/skyline_daily_synthetic_reference.skyd
madic/__init__.py
madic/command_line.py
madic/interference.py
madic/io.py
madic/plotting.py
madic/qc.py
madic/utils.py
madic/version.py
madic.egg-info/PKG-INFO
madic.egg-info/SOURCES.txt
madic.egg-info/dependency_links.txt
madic.egg-info/entry_points.txt
madic.egg-info/requires.txt
madic.egg-info/top_level.txt
madic/tests/__init__.py
madic/tests/test_integration.py
madic/tests/test_interference.py
madic/tests/test_io.py
madic/tests/test_plotting.py
madic/tests/test_qc.py
madic/tests/data/for_testing_data.csv
madic/tests/data/for_testing_summary.csv
static/madic_skyline_daily_transition_report_and_chromatogram.skyr
static/overview.png