Metadata-Version: 1.1
Name: madic
Version: 0.1.0
Summary: MAtrix-Dependent Interference Correction of targeted mass spectrometry data
Home-page: https://github.com/dcroote/madic
Author: Derek Croote
Author-email: dcroote@stanford.edu
License: UNKNOWN
Keywords: mass spectrometry SRM MRM Skyline LC-MS/MS
Platform: UNKNOWN
Classifier: Intended Audience :: Science/Research
Classifier: License :: OSI Approved :: BSD License
Classifier: Programming Language :: Python :: 2.7
Classifier: Programming Language :: Python :: 3.4
Classifier: Programming Language :: Python :: 3.5
Classifier: Programming Language :: Python :: 3.6
Classifier: Topic :: Scientific/Engineering :: Bio-Informatics
Classifier: Operating System :: Microsoft :: Windows
Classifier: Operating System :: MacOS
Classifier: Operating System :: POSIX
Classifier: Operating System :: Unix
